<?xml version="1.0" encoding="utf8" standalone="no" ?>
<vehicleTypes>
	<Lindner>
		<type name="mr_tractor_steerableExtension" className="Vehicle" filename="$dataS/scripts/vehicles/Vehicle.lua">
			<specialization name="realisticVehicle" />

			<specialization name="motorized" />
			<specialization name="steerable" />
			<specialization name="animatedVehicle" />
			<specialization name="cylindered" />
			<specialization name="foldable" />
			<specialization name="hirable" />
			<specialization name="aiTractor" />
			<specialization name="bunkerSiloCompacter" />
			<specialization name="honk" />
			<specialization name="pdlc_lindnerUnitracPack.steerableExtension" />

			<specialization name="realisticMotorized" />
			<specialization name="realisticSteerable" />
		</type>
	</Lindner>

	<!-- ################################################## -->

	<Titanium>
		<type name="mr_tractor_wheelExtension" className="Vehicle" filename="$dataS/scripts/vehicles/Vehicle.lua">
			<specialization name="realisticVehicle" />

			<specialization name="motorized" />
			<specialization name="steerable" />
			<specialization name="pdlc_titaniumAddon.wheelExtension" />
			<specialization name="animatedVehicle" />
			<specialization name="cylindered" />
			<specialization name="foldable" />
			<specialization name="hirable" />
			<specialization name="aiTractor" />
			<specialization name="bunkerSiloCompacter" />
			<specialization name="honk" />
			<specialization name="pdlc_titaniumAddon.steerableExtension" />

			<specialization name="realisticMotorized" />
			<specialization name="realisticSteerable" />
		</type>

		<type name="mr_sowingMachine_foldableRidgeMarker" className="Vehicle" filename="$dataS/scripts/vehicles/Vehicle.lua">
			<specialization name="realisticVehicle" />

			<specialization name="attachable" />
			<specialization name="animatedVehicle" />
			<specialization name="cylindered" />
			<specialization name="fillable" />
			<specialization name="sowingMachine" />
			<specialization name="foldable" />
			<specialization name="ridgeMarker" />
			<specialization name="pdlc_titaniumAddon.visualWheels" />
			<specialization name="pdlc_titaniumAddon.foldableRidgeMarker" />

			<specialization name="realisticTool" />
		</type>

		<type name="mr_combine_extended" className="Vehicle" filename="$dataS/scripts/vehicles/Vehicle.lua">
			<specialization name="realisticVehicle" />

			<specialization name="animatedVehicle" />
			<specialization name="cylindered" />
			<specialization name="foldable" />
			<specialization name="motorized" />
			<specialization name="steerable" />
			<specialization name="pdlc_titaniumAddon.steerableExtension" />
			<specialization name="combine" />
			<specialization name="pdlc_titaniumAddon.combineExtension" />
			<specialization name="hirable" />
			<specialization name="aiCombine" />
			<specialization name="honk" />
			<specialization name="bunkerSiloCompacter" />
			<specialization name="mouseControlsVehicle" />
			<specialization name="pdlc_titaniumAddon.turnedOnRotationNodes" />
			<specialization name="pdlc_titaniumAddon.chopperSwitcher" />

			<specialization name="realisticMotorized" />
			<specialization name="realisticSteerable" />
			<specialization name="realisticCombine" />
		</type>

		<type name="mr_cutter_mouseControlled" className="Vehicle" filename="$dataS/scripts/vehicles/Vehicle.lua">
			<specialization name="realisticVehicle" />

			<specialization name="attachable" />
			<specialization name="animatedVehicle" />
			<specialization name="mouseControlsVehicle" />
			<specialization name="cylindered" />
			<specialization name="cutter" />
			<specialization name="mountable" />
			<specialization name="foldable" />

			<specialization name="realisticCutter" />
		</type>

		<type name="mr_augerWagon" className="Vehicle" filename="$dataS/scripts/vehicles/Vehicle.lua">
			<specialization name="realisticVehicle" />

			<specialization name="attachable" />
			<specialization name="animatedVehicle" />
			<specialization name="cylindered" />
			<specialization name="fillable" />
			<specialization name="trailer" />
			<specialization name="foldable" />
			<specialization name="pdlc_titaniumAddon.augerWagon" />

			<specialization name="augerWagonPowerConsumption" />
			<specialization name="realisticMovingTool" />
		</type>
	</Titanium>

	<!-- ################################################## -->

	<Ursus>
	</Ursus>
</vehicleTypes>